combination_builder/Combinations.py
combination_builder/__init__.py
combination_builder-0.1.0.dist-info/LICENSE
combination_builder-0.1.0.dist-info/METADATA
combination_builder-0.1.0.dist-info/WHEEL
combination_builder-0.1.0.dist-info/top_level.txt
combination_builder-0.1.0.dist-info/RECORD
