Metadata-Version: 2.1
Name: combination-builder
Version: 0.1.0
Summary: Provides a framework for easily constructing work list files for creation of combinations of substances for high throughput screening
Home-page: https://github.com/StJude-HTB/Echo-Combination-Builder
Author: Duane Currier
Author-email: duane.currier@stjude.org
License: UNKNOWN
Project-URL: Bug Tracker, https://github.com/StJude-HTB/Echo-Combination-Builder/issues
Platform: UNKNOWN
Classifier: Programming Language :: Python :: 3
Classifier: License :: OSI Approved :: MIT License
Classifier: Operating System :: OS Independent
Requires-Python: >=3.8
License-File: LICENSE
